Metadata-Version: 2.1
Name: odoo-addon-website_sale_stock_available
Version: 18.0.1.0.0.1
Requires-Python: >=3.10
Requires-Dist: odoo-addon-stock_available==18.0.*
Requires-Dist: odoo==18.0.*
Summary: Display 'Available to promise' in shop online instead of 'Free To Use Quantity'
Home-page: https://github.com/OCA/e-commerce
License: AGPL-3
Author: Tecnativa, Odoo Community Association (OCA)
Author-email: support@odoo-community.org
Classifier: Programming Language :: Python
Classifier: Framework :: Odoo
Classifier: Framework :: Odoo :: 18.0
Classifier: License :: OSI Approved :: GNU Affero General Public License v3
